fastdsd/__init__.py
fastdsd/__main__.py
fastdsd/calcDSD.py
fastdsd/directed_augment.py
fastdsd/dsdcore.py
fastdsd/dsdio.py
fastdsd-1.0.1.dist-info/LICENSE
fastdsd-1.0.1.dist-info/METADATA
fastdsd-1.0.1.dist-info/WHEEL
fastdsd-1.0.1.dist-info/entry_points.txt
fastdsd-1.0.1.dist-info/top_level.txt
fastdsd-1.0.1.dist-info/RECORD
