Metadata-Version: 2.1
Name: fastdsd
Version: 1.0.1
Summary: Combining DSD (Cao et al. 2013, 2014) runtime optimizations from reemagit for a fast, optimized version of DSD / cDSD
Author: Mengfei Cao, reemagit
Author-email: Samuel Sledzieski <samsl@mit.edu>
License: GNU AFFERO GENERAL PUBLIC LICENSE
Project-URL: Homepage, https://github.com/samsledje/fastDSD
Project-URL: Issues, https://github.com/samsledje/fastDSD/issues
Classifier: Programming Language :: Python :: 3
Classifier: License :: OSI Approved :: MIT License
Classifier: Operating System :: OS Independent
Requires-Python: >=3.9
License-File: LICENSE
Requires-Dist: numpy
Requires-Dist: scipy
Requires-Dist: pandas
Requires-Dist: networkx
